roblox_auth/__init__.py
roblox_auth/hi.py
roblox_auth/main.py
roblox_auth/webdriver.py
roblox_auth-0.5.2.dist-info/METADATA
roblox_auth-0.5.2.dist-info/WHEEL
roblox_auth-0.5.2.dist-info/top_level.txt
roblox_auth-0.5.2.dist-info/RECORD
