Metadata-Version: 2.1
Name: roblox_auth
Version: 0.5.2
